Authr/__init__.py
Authr/auth_scrape_functions.py
Authr/authr.py
Authr/authr_tests.py
Authr/map_functions.py
Authr/shodan_functions.py
authr-1.3.3.dist-info/METADATA
authr-1.3.3.dist-info/RECORD
authr-1.3.3.dist-info/WHEEL
authr-1.3.3.dist-info/top_level.txt
