Metadata-Version: 2.1
Name: authr
Version: 1.3.3
Summary: A visualization python package that can extract information from any server log (i.e. HTTP server/Django/Auth/etc), reverse-search the data, and visualize the origination of the authentication attempts.
Home-page: https://github.com/JLDevOps/Authr
Author: Jimmy Le (JLDevOps)
Author-email: jldevops@gmail.com
License: UNKNOWN
Platform: UNKNOWN
Classifier: Programming Language :: Python :: 3
Classifier: License :: OSI Approved :: MIT License
Classifier: Operating System :: OS Independent
